git_file_mapper/__init__.py
git_file_mapper/cli.py
git_file_mapper/mapper.py
git_file_mapper-1.0.1.dist-info/LICENCE
git_file_mapper-1.0.1.dist-info/METADATA
git_file_mapper-1.0.1.dist-info/WHEEL
git_file_mapper-1.0.1.dist-info/entry_points.txt
git_file_mapper-1.0.1.dist-info/top_level.txt
git_file_mapper-1.0.1.dist-info/RECORD
