Metadata-Version: 2.1
Name: git-file-mapper
Version: 1.0.1
Summary: A programme that applies a map operation to files in git
Home-page: https://github.com/MatthewWilkes/git_file_mapper
Author: Matthew Wilkes
Author-email: matt@matthewwilkes.name
License: BSD
Platform: UNKNOWN
Classifier: Programming Language :: Python :: 3
Classifier: Programming Language :: Python :: 3.8
Requires-Dist: gitpython
Requires-Dist: click
